<annotation>
	<folder>remain</folder>
	<filename>with_mask657.jpeg</filename>
	<path>C:\Users\HP\Desktop\artifacts\final-mask\remain\with_mask657.jpeg</path>
	<source>
		<database>Unknown</database>
	</source>
	<size>
		<width>275</width>
		<height>183</height>
		<depth>3</depth>
	</size>
	<segmented>0</segmented>
	<object>
		<name>Mask</name>
		<pose>Unspecified</pose>
		<truncated>0</truncated>
		<difficult>0</difficult>
		<bndbox>
			<xmin>105</xmin>
			<ymin>62</ymin>
			<xmax>146</xmax>
			<ymax>110</ymax>
		</bndbox>
	</object>
</annotation>
